elastic3rd/__init__.py
elastic3rd/elastic.py
elastic3rd/esutils.py
elastic3rd/crystal/__init__.py
elastic3rd/crystal/deform.py
elastic3rd/crystal/lattice.py
elastic3rd/energy/__init__.py
elastic3rd/energy/castep.py
elastic3rd/energy/energyrun
elastic3rd/energy/glue.py
elastic3rd/energy/vasp.py
elastic3rd/post/__init__.py
elastic3rd/post/esfit.py
elastic3rd/post/post.py
elastic3rd/scripts/__init__.py
elastic3rd/scripts/run_elastic3rd.py
elastic3rd/symmetry/__init__.py
elastic3rd/symmetry/symdata.py
elastic3rd/symmetry/symmetry.py
ELASTIC3rd-2.5.1.dist-info/METADATA
ELASTIC3rd-2.5.1.dist-info/WHEEL
ELASTIC3rd-2.5.1.dist-info/entry_points.txt
ELASTIC3rd-2.5.1.dist-info/top_level.txt
ELASTIC3rd-2.5.1.dist-info/RECORD
